{
  "data": [
    {
      "agent-features": null,
      "base-image-id": null,
      "compartment-id": null,
      "create-image-allowed": true,
      "defined-tags": {},
      "display-name": "Windows-Server-2016-Standard-Edition-VM-Gen2-2019.10.09-0",
      "freeform-tags": {},
      "id": "ocid1.image.oc1.eu-frankfurt-1.aaaaaaaautcl2r57xznasoyp5e7c33w4kyqu4xkfdkto7e2ksthquwqogmya",
      "launch-mode": "NATIVE",
      "launch-options": {
        "boot-volume-type": "PARAVIRTUALIZED",
        "firmware": "UEFI_64",
        "is-consistent-volume-naming-enabled": false,
        "is-pv-encryption-in-transit-enabled": true,
        "network-type": "PARAVIRTUALIZED",
        "remote-data-volume-type": "PARAVIRTUALIZED"
      },
      "lifecycle-state": "AVAILABLE",
      "operating-system": "Windows",
      "operating-system-version": "Server 2016 Standard",
      "size-in-mbs": 262144,
      "time-created": "2019-10-10T04:03:32.489000+00:00"
    },
    {
      "agent-features": null,
      "base-image-id": null,
      "compartment-id": null,
      "create-image-allowed": true,
      "defined-tags": {},
      "display-name": "Windows-Server-2016-Standard-Edition-VM-Gen2-2019.09.26-0",
      "freeform-tags": {},
      "id": "ocid1.image.oc1.eu-frankfurt-1.aaaaaaaar3oenzksk6lgsz3y6scps2nmxkcrsc473zmklzwcdqinv6f7ev3a",
      "launch-mode": "NATIVE",
      "launch-options": {
        "boot-volume-type": "PARAVIRTUALIZED",
        "firmware": "UEFI_64",
        "is-consistent-volume-naming-enabled": false,
        "is-pv-encryption-in-transit-enabled": true,
        "network-type": "PARAVIRTUALIZED",
        "remote-data-volume-type": "PARAVIRTUALIZED"
      },
      "lifecycle-state": "AVAILABLE",
      "operating-system": "Windows",
      "operating-system-version": "Server 2016 Standard",
      "size-in-mbs": 262144,
      "time-created": "2019-09-26T19:30:10.318000+00:00"
    },
    {
      "agent-features": null,
      "base-image-id": null,
      "compartment-id": null,
      "create-image-allowed": true,
      "defined-tags": {},
      "display-name": "Windows-Server-2016-Standard-Edition-VM-Gen2-2019.08.15-0",
      "freeform-tags": {},
      "id": "ocid1.image.oc1.eu-frankfurt-1.aaaaaaaazlvwdcp5ujhsfrogqfdjtupsikqe252rqx6j2bd3zxbmsgufcleq",
      "launch-mode": "NATIVE",
      "launch-options": {
        "boot-volume-type": "PARAVIRTUALIZED",
        "firmware": "UEFI_64",
        "is-consistent-volume-naming-enabled": false,
        "is-pv-encryption-in-transit-enabled": true,
        "network-type": "PARAVIRTUALIZED",
        "remote-data-volume-type": "PARAVIRTUALIZED"
      },
      "lifecycle-state": "AVAILABLE",
      "operating-system": "Windows",
      "operating-system-version": "Server 2016 Standard",
      "size-in-mbs": 262144,
      "time-created": "2019-08-15T04:48:12.154000+00:00"
    },
    {
      "agent-features": null,
      "base-image-id": null,
      "compartment-id": null,
      "create-image-allowed": true,
      "defined-tags": {},
      "display-name": "Windows-Server-2016-Standard-Edition-VM-B1-2019.10.09-0",
      "freeform-tags": {},
      "id": "ocid1.image.oc1.eu-frankfurt-1.aaaaaaaai4ilvzwkiabqccamvb67ptskaunra5qttfrobccmmuqjryyx22zq",
      "launch-mode": "PARAVIRTUALIZED",
      "launch-options": {
        "boot-volume-type": "PARAVIRTUALIZED",
        "firmware": "UEFI_64",
        "is-consistent-volume-naming-enabled": false,
        "is-pv-encryption-in-transit-enabled": true,
        "network-type": "PARAVIRTUALIZED",
        "remote-data-volume-type": "PARAVIRTUALIZED"
      },
      "lifecycle-state": "AVAILABLE",
      "operating-system": "Windows",
      "operating-system-version": "Server 2016 Standard",
      "size-in-mbs": 262144,
      "time-created": "2019-10-10T03:58:33.632000+00:00"
    },
    {
      "agent-features": null,
      "base-image-id": null,
      "compartment-id": null,
      "create-image-allowed": true,
      "defined-tags": {},
      "display-name": "Windows-Server-2016-Standard-Edition-VM-B1-2019.09.26-0",
      "freeform-tags": {},
      "id": "ocid1.image.oc1.eu-frankfurt-1.aaaaaaaaruw54qzdku5e6ikqrttqsbdbucj2l6mitcegydu3i4if2cjmmrya",
      "launch-mode": "PARAVIRTUALIZED",
      "launch-options": {
        "boot-volume-type": "PARAVIRTUALIZED",
        "firmware": "UEFI_64",
        "is-consistent-volume-naming-enabled": false,
        "is-pv-encryption-in-transit-enabled": true,
        "network-type": "PARAVIRTUALIZED",
        "remote-data-volume-type": "PARAVIRTUALIZED"
      },
      "lifecycle-state": "AVAILABLE",
      "operating-system": "Windows",
      "operating-system-version": "Server 2016 Standard",
      "size-in-mbs": 262144,
      "time-created": "2019-09-26T06:25:02+00:00"
    },
    {
      "agent-features": null,
      "base-image-id": null,
      "compartment-id": null,
      "create-image-allowed": true,
      "defined-tags": {},
      "display-name": "Windows-Server-2016-Standard-Edition-VM-2019.10.12-0",
      "freeform-tags": {},
      "id": "ocid1.image.oc1.eu-frankfurt-1.aaaaaaaadbgnaa2iofzovexmf4v3honkhtwzy37vix7f32ygvfjd2jqkevuq",
      "launch-mode": "NATIVE",
      "launch-options": {
        "boot-volume-type": "PARAVIRTUALIZED",
        "firmware": "UEFI_64",
        "is-consistent-volume-naming-enabled": false,
        "is-pv-encryption-in-transit-enabled": true,
        "network-type": "VFIO",
        "remote-data-volume-type": "PARAVIRTUALIZED"
      },
      "lifecycle-state": "AVAILABLE",
      "operating-system": "Windows",
      "operating-system-version": "Server 2016 Standard",
      "size-in-mbs": 262144,
      "time-created": "2019-10-15T00:42:35.590000+00:00"
    },
    {
      "agent-features": null,
      "base-image-id": null,
      "compartment-id": null,
      "create-image-allowed": true,
      "defined-tags": {},
      "display-name": "Windows-Server-2016-Datacenter-Edition-BM-Gen2-E2-2019.10.09-0",
      "freeform-tags": {},
      "id": "ocid1.image.oc1.eu-frankfurt-1.aaaaaaaar2g3ptazz62gm46a33nvgk7eowghgdf4urlsv2ewpj3mnqmievuq",
      "launch-mode": "NATIVE",
      "launch-options": {
        "boot-volume-type": "PARAVIRTUALIZED",
        "firmware": "UEFI_64",
        "is-consistent-volume-naming-enabled": false,
        "is-pv-encryption-in-transit-enabled": true,
        "network-type": "VFIO",
        "remote-data-volume-type": "PARAVIRTUALIZED"
      },
      "lifecycle-state": "AVAILABLE",
      "operating-system": "Windows",
      "operating-system-version": "Server 2016 Datacenter",
      "size-in-mbs": 262144,
      "time-created": "2019-10-11T20:18:28.328000+00:00"
    },
    {
      "agent-features": null,
      "base-image-id": null,
      "compartment-id": null,
      "create-image-allowed": true,
      "defined-tags": {},
      "display-name": "Windows-Server-2016-Datacenter-Edition-BM-Gen2-E2-2019.08.16-0",
      "freeform-tags": {},
      "id": "ocid1.image.oc1.eu-frankfurt-1.aaaaaaaah2drw2fircgmho2wlnmdc6xsrzzv5b6qckcx43zcbvfixcokpazq",
      "launch-mode": "NATIVE",
      "launch-options": {
        "boot-volume-type": "PARAVIRTUALIZED",
        "firmware": "UEFI_64",
        "is-consistent-volume-naming-enabled": false,
        "is-pv-encryption-in-transit-enabled": true,
        "network-type": "VFIO",
        "remote-data-volume-type": "PARAVIRTUALIZED"
      },
      "lifecycle-state": "AVAILABLE",
      "operating-system": "Windows",
      "operating-system-version": "Server 2016 Datacenter",
      "size-in-mbs": 262144,
      "time-created": "2019-08-16T18:15:47.764000+00:00"
    },
    {
      "agent-features": null,
      "base-image-id": null,
      "compartment-id": null,
      "create-image-allowed": true,
      "defined-tags": {},
      "display-name": "Windows-Server-2016-Datacenter-Edition-BM-Gen2-E2-2018.10.17-0",
      "freeform-tags": {},
      "id": "ocid1.image.oc1.eu-frankfurt-1.aaaaaaaa7t55spn44covtcmul4jhcy4g53l6xljq6ngtsgdq4mohkocsbbmq",
      "launch-mode": "NATIVE",
      "launch-options": {
        "boot-volume-type": "PARAVIRTUALIZED",
        "firmware": "UEFI_64",
        "is-consistent-volume-naming-enabled": false,
        "is-pv-encryption-in-transit-enabled": false,
        "network-type": "VFIO",
        "remote-data-volume-type": "PARAVIRTUALIZED"
      },
      "lifecycle-state": "AVAILABLE",
      "operating-system": "Windows",
      "operating-system-version": "Server 2016 Datacenter",
      "size-in-mbs": 262144,
      "time-created": "2018-10-17T10:13:27.505000+00:00"
    },
    {
      "agent-features": null,
      "base-image-id": null,
      "compartment-id": null,
      "create-image-allowed": true,
      "defined-tags": {},
      "display-name": "Windows-Server-2016-Datacenter-Edition-BM-Gen2-DenseIO-2019.10.09-0",
      "freeform-tags": {},
      "id": "ocid1.image.oc1.eu-frankfurt-1.aaaaaaaahde6uqfvau5ezsw5igsigwyof77w7t6bbbdgewww5snn3pw645la",
      "launch-mode": "NATIVE",
      "launch-options": {
        "boot-volume-type": "PARAVIRTUALIZED",
        "firmware": "UEFI_64",
        "is-consistent-volume-naming-enabled": false,
        "is-pv-encryption-in-transit-enabled": true,
        "network-type": "VFIO",
        "remote-data-volume-type": "PARAVIRTUALIZED"
      },
      "lifecycle-state": "AVAILABLE",
      "operating-system": "Windows",
      "operating-system-version": "Server 2016 Datacenter",
      "size-in-mbs": 262144,
      "time-created": "2019-10-11T20:26:11.066000+00:00"
    },
    {
      "agent-features": null,
      "base-image-id": null,
      "compartment-id": null,
      "create-image-allowed": true,
      "defined-tags": {},
      "display-name": "Windows-Server-2016-Datacenter-Edition-BM-Gen2-DenseIO-2019.09.21-0",
      "freeform-tags": {},
      "id": "ocid1.image.oc1.eu-frankfurt-1.aaaaaaaaeo3tufhokppphc2bcihvoxjzqmyzcwdieioshb2j5ibdz7losksa",
      "launch-mode": "NATIVE",
      "launch-options": {
        "boot-volume-type": "PARAVIRTUALIZED",
        "firmware": "UEFI_64",
        "is-consistent-volume-naming-enabled": false,
        "is-pv-encryption-in-transit-enabled": true,
        "network-type": "VFIO",
        "remote-data-volume-type": "PARAVIRTUALIZED"
      },
      "lifecycle-state": "AVAILABLE",
      "operating-system": "Windows",
      "operating-system-version": "Server 2016 Datacenter",
      "size-in-mbs": 262144,
      "time-created": "2019-09-24T22:19:06.459000+00:00"
    },
    {
      "agent-features": null,
      "base-image-id": null,
      "compartment-id": null,
      "create-image-allowed": true,
      "defined-tags": {},
      "display-name": "Windows-Server-2016-Datacenter-Edition-BM-Gen2-DenseIO-2019.08.14-0",
      "freeform-tags": {},
      "id": "ocid1.image.oc1.eu-frankfurt-1.aaaaaaaaaxdopjpkv5rubcs3iy5d7qmzi7ee5ktsxjxyc4gz3b4pwfphyyra",
      "launch-mode": "NATIVE",
      "launch-options": {
        "boot-volume-type": "PARAVIRTUALIZED",
        "firmware": "UEFI_64",
        "is-consistent-volume-naming-enabled": false,
        "is-pv-encryption-in-transit-enabled": true,
        "network-type": "VFIO",
        "remote-data-volume-type": "PARAVIRTUALIZED"
      },
      "lifecycle-state": "AVAILABLE",
      "operating-system": "Windows",
      "operating-system-version": "Server 2016 Datacenter",
      "size-in-mbs": 262144,
      "time-created": "2019-08-15T16:36:09.091000+00:00"
    },
    {
      "agent-features": null,
      "base-image-id": null,
      "compartment-id": null,
      "create-image-allowed": true,
      "defined-tags": {},
      "display-name": "Windows-Server-2016-Datacenter-Edition-BM-Gen2-2019.10.09-0",
      "freeform-tags": {},
      "id": "ocid1.image.oc1.eu-frankfurt-1.aaaaaaaazdcmkdfohc6tv4wxo3y77u5dlt47slqp26pxbgchpq7cxskmryjq",
      "launch-mode": "NATIVE",
      "launch-options": {
        "boot-volume-type": "PARAVIRTUALIZED",
        "firmware": "UEFI_64",
        "is-consistent-volume-naming-enabled": false,
        "is-pv-encryption-in-transit-enabled": true,
        "network-type": "VFIO",
        "remote-data-volume-type": "PARAVIRTUALIZED"
      },
      "lifecycle-state": "AVAILABLE",
      "operating-system": "Windows",
      "operating-system-version": "Server 2016 Datacenter",
      "size-in-mbs": 262144,
      "time-created": "2019-10-11T20:22:25.160000+00:00"
    },
    {
      "agent-features": null,
      "base-image-id": null,
      "compartment-id": null,
      "create-image-allowed": true,
      "defined-tags": {},
      "display-name": "Windows-Server-2016-Datacenter-Edition-BM-Gen2-2019.09.26-0",
      "freeform-tags": {},
      "id": "ocid1.image.oc1.eu-frankfurt-1.aaaaaaaarfbb6wqlxkiyjwjwiaoeiw26tws6gwh3jqrnb7s3x5u2qwexwjbq",
      "launch-mode": "NATIVE",
      "launch-options": {
        "boot-volume-type": "PARAVIRTUALIZED",
        "firmware": "UEFI_64",
        "is-consistent-volume-naming-enabled": false,
        "is-pv-encryption-in-transit-enabled": true,
        "network-type": "VFIO",
        "remote-data-volume-type": "PARAVIRTUALIZED"
      },
      "lifecycle-state": "AVAILABLE",
      "operating-system": "Windows",
      "operating-system-version": "Server 2016 Datacenter",
      "size-in-mbs": 262144,
      "time-created": "2019-09-26T05:41:57.837000+00:00"
    },
    {
      "agent-features": null,
      "base-image-id": null,
      "compartment-id": null,
      "create-image-allowed": true,
      "defined-tags": {},
      "display-name": "Windows-Server-2016-Datacenter-Edition-BM-Gen2-2019.08.14-0",
      "freeform-tags": {},
      "id": "ocid1.image.oc1.eu-frankfurt-1.aaaaaaaameu34kc6pscmvyklr6tqeov7zelrnhhtnw7neqrruuyzkpnaenfa",
      "launch-mode": "NATIVE",
      "launch-options": {
        "boot-volume-type": "PARAVIRTUALIZED",
        "firmware": "UEFI_64",
        "is-consistent-volume-naming-enabled": false,
        "is-pv-encryption-in-transit-enabled": true,
        "network-type": "VFIO",
        "remote-data-volume-type": "PARAVIRTUALIZED"
      },
      "lifecycle-state": "AVAILABLE",
      "operating-system": "Windows",
      "operating-system-version": "Server 2016 Datacenter",
      "size-in-mbs": 262144,
      "time-created": "2019-08-15T04:14:01.344000+00:00"
    },
    {
      "agent-features": null,
      "base-image-id": null,
      "compartment-id": null,
      "create-image-allowed": true,
      "defined-tags": {},
      "display-name": "Windows-Server-2012-R2-Standard-Edition-VM-Gen2-E2-2019.10.09-0",
      "freeform-tags": {},
      "id": "ocid1.image.oc1.eu-frankfurt-1.aaaaaaaal4dnuw6iuwbwampj5sfrkdvbsudpftosxce77yea3i6akiecrtaa",
      "launch-mode": "PARAVIRTUALIZED",
      "launch-options": {
        "boot-volume-type": "PARAVIRTUALIZED",
        "firmware": "UEFI_64",
        "is-consistent-volume-naming-enabled": false,
        "is-pv-encryption-in-transit-enabled": true,
        "network-type": "PARAVIRTUALIZED",
        "remote-data-volume-type": "PARAVIRTUALIZED"
      },
      "lifecycle-state": "AVAILABLE",
      "operating-system": "Windows",
      "operating-system-version": "Server 2012 R2 Standard",
      "size-in-mbs": 262144,
      "time-created": "2019-10-15T00:35:52.311000+00:00"
    },
    {
      "agent-features": null,
      "base-image-id": null,
      "compartment-id": null,
      "create-image-allowed": true,
      "defined-tags": {},
      "display-name": "Windows-Server-2012-R2-Standard-Edition-VM-Gen2-E2-2019.08.21-0",
      "freeform-tags": {},
      "id": "ocid1.image.oc1.eu-frankfurt-1.aaaaaaaatnpeomvnjxazodajk56euqg4nlpzknhzymqqb6pkl4pthazvr2fa",
      "launch-mode": "PARAVIRTUALIZED",
      "launch-options": {
        "boot-volume-type": "PARAVIRTUALIZED",
        "firmware": "UEFI_64",
        "is-consistent-volume-naming-enabled": false,
        "is-pv-encryption-in-transit-enabled": true,
        "network-type": "PARAVIRTUALIZED",
        "remote-data-volume-type": "PARAVIRTUALIZED"
      },
      "lifecycle-state": "AVAILABLE",
      "operating-system": "Windows",
      "operating-system-version": "Server 2012 R2 Standard",
      "size-in-mbs": 262144,
      "time-created": "2019-08-21T18:11:00.055000+00:00"
    },
    {
      "agent-features": null,
      "base-image-id": null,
      "compartment-id": null,
      "create-image-allowed": true,
      "defined-tags": {},
      "display-name": "Windows-Server-2012-R2-Standard-Edition-VM-Gen2-E2-2019.06.13-0",
      "freeform-tags": {},
      "id": "ocid1.image.oc1.eu-frankfurt-1.aaaaaaaavlvff3nhhauwecv7jtvqgbkx5i3w2cmsznqfa3h5zxf4lwdaf6sq",
      "launch-mode": "PARAVIRTUALIZED",
      "launch-options": {
        "boot-volume-type": "PARAVIRTUALIZED",
        "firmware": "UEFI_64",
        "is-consistent-volume-naming-enabled": false,
        "is-pv-encryption-in-transit-enabled": true,
        "network-type": "PARAVIRTUALIZED",
        "remote-data-volume-type": "PARAVIRTUALIZED"
      },
      "lifecycle-state": "AVAILABLE",
      "operating-system": "Windows",
      "operating-system-version": "Server 2012 R2 Standard",
      "size-in-mbs": 262144,
      "time-created": "2019-06-17T23:36:10.071000+00:00"
    },
    {
      "agent-features": null,
      "base-image-id": null,
      "compartment-id": null,
      "create-image-allowed": true,
      "defined-tags": {},
      "display-name": "Windows-Server-2012-R2-Standard-Edition-VM-Gen2-E2-2019.05.15-0",
      "freeform-tags": {},
      "id": "ocid1.image.oc1.eu-frankfurt-1.aaaaaaaaj5kwq64dybtgo4dkm7mqjok4wqh2oj3orlvj4n7jviugdsoswlha",
      "launch-mode": "PARAVIRTUALIZED",
      "launch-options": {
        "boot-volume-type": "PARAVIRTUALIZED",
        "firmware": "UEFI_64",
        "is-consistent-volume-naming-enabled": false,
        "is-pv-encryption-in-transit-enabled": true,
        "network-type": "PARAVIRTUALIZED",
        "remote-data-volume-type": "PARAVIRTUALIZED"
      },
      "lifecycle-state": "AVAILABLE",
      "operating-system": "Windows",
      "operating-system-version": "Server 2012 R2 Standard",
      "size-in-mbs": 262144,
      "time-created": "2019-05-15T04:58:42.122000+00:00"
    },
    {
      "agent-features": null,
      "base-image-id": null,
      "compartment-id": null,
      "create-image-allowed": true,
      "defined-tags": {},
      "display-name": "Windows-Server-2012-R2-Standard-Edition-VM-Gen2-2019.10.09-0",
      "freeform-tags": {},
      "id": "ocid1.image.oc1.eu-frankfurt-1.aaaaaaaahlw4sii7bfqilh6dbo3o4kl6edbc24mah2aenzrceuc7tsigmtpq",
      "launch-mode": "NATIVE",
      "launch-options": {
        "boot-volume-type": "PARAVIRTUALIZED",
        "firmware": "UEFI_64",
        "is-consistent-volume-naming-enabled": false,
        "is-pv-encryption-in-transit-enabled": true,
        "network-type": "VFIO",
        "remote-data-volume-type": "PARAVIRTUALIZED"
      },
      "lifecycle-state": "AVAILABLE",
      "operating-system": "Windows",
      "operating-system-version": "Server 2012 R2 Standard",
      "size-in-mbs": 262144,
      "time-created": "2019-10-10T22:29:27.196000+00:00"
    },
    {
      "agent-features": null,
      "base-image-id": null,
      "compartment-id": null,
      "create-image-allowed": true,
      "defined-tags": {},
      "display-name": "Windows-Server-2012-R2-Standard-Edition-VM-Gen2-2019.08.21-0",
      "freeform-tags": {},
      "id": "ocid1.image.oc1.eu-frankfurt-1.aaaaaaaaugwetgpq2crukmimxod644llnqabm3ab2yrp2mal33pjiaowfdua",
      "launch-mode": "NATIVE",
      "launch-options": {
        "boot-volume-type": "PARAVIRTUALIZED",
        "firmware": "UEFI_64",
        "is-consistent-volume-naming-enabled": false,
        "is-pv-encryption-in-transit-enabled": true,
        "network-type": "VFIO",
        "remote-data-volume-type": "PARAVIRTUALIZED"
      },
      "lifecycle-state": "AVAILABLE",
      "operating-system": "Windows",
      "operating-system-version": "Server 2012 R2 Standard",
      "size-in-mbs": 262144,
      "time-created": "2019-08-21T17:39:10.854000+00:00"
    },
    {
      "agent-features": null,
      "base-image-id": null,
      "compartment-id": null,
      "create-image-allowed": true,
      "defined-tags": {},
      "display-name": "Windows-Server-2012-R2-Standard-Edition-VM-Gen2-2019.06.13-0",
      "freeform-tags": {},
      "id": "ocid1.image.oc1.eu-frankfurt-1.aaaaaaaaty6rhps6edxjkdki2mgfxlfblev4vkmvaq7gahbxl2hpirwdviaq",
      "launch-mode": "NATIVE",
      "launch-options": {
        "boot-volume-type": "PARAVIRTUALIZED",
        "firmware": "UEFI_64",
        "is-consistent-volume-naming-enabled": false,
        "is-pv-encryption-in-transit-enabled": true,
        "network-type": "VFIO",
        "remote-data-volume-type": "PARAVIRTUALIZED"
      },
      "lifecycle-state": "AVAILABLE",
      "operating-system": "Windows",
      "operating-system-version": "Server 2012 R2 Standard",
      "size-in-mbs": 262144,
      "time-created": "2019-06-13T02:41:12.824000+00:00"
    },
    {
      "agent-features": null,
      "base-image-id": null,
      "compartment-id": null,
      "create-image-allowed": true,
      "defined-tags": {},
      "display-name": "Windows-Server-2012-R2-Standard-Edition-VM-Gen2-2019.05.14-0",
      "freeform-tags": {},
      "id": "ocid1.image.oc1.eu-frankfurt-1.aaaaaaaaeok5pffgfartydpvb2h2chggqsly2drepuw3vcgyeg5g3ad7xr2a",
      "launch-mode": "NATIVE",
      "launch-options": {
        "boot-volume-type": "PARAVIRTUALIZED",
        "firmware": "UEFI_64",
        "is-consistent-volume-naming-enabled": false,
        "is-pv-encryption-in-transit-enabled": true,
        "network-type": "VFIO",
        "remote-data-volume-type": "PARAVIRTUALIZED"
      },
      "lifecycle-state": "AVAILABLE",
      "operating-system": "Windows",
      "operating-system-version": "Server 2012 R2 Standard",
      "size-in-mbs": 262144,
      "time-created": "2019-05-15T03:54:17.845000+00:00"
    },
    {
      "agent-features": null,
      "base-image-id": null,
      "compartment-id": null,
      "create-image-allowed": true,
      "defined-tags": {},
      "display-name": "Windows-Server-2012-R2-Standard-Edition-VM-2019.10.09-0",
      "freeform-tags": {},
      "id": "ocid1.image.oc1.eu-frankfurt-1.aaaaaaaalh33vagzpgm7g7xweuahp45ycjpzvsmfidb23q4fji27un6tkzyq",
      "launch-mode": "NATIVE",
      "launch-options": {
        "boot-volume-type": "PARAVIRTUALIZED",
        "firmware": "UEFI_64",
        "is-consistent-volume-naming-enabled": false,
        "is-pv-encryption-in-transit-enabled": true,
        "network-type": "VFIO",
        "remote-data-volume-type": "PARAVIRTUALIZED"
      },
      "lifecycle-state": "AVAILABLE",
      "operating-system": "Windows",
      "operating-system-version": "Server 2012 R2 Standard",
      "size-in-mbs": 262144,
      "time-created": "2019-10-10T00:22:49.121000+00:00"
    },
    {
      "agent-features": null,
      "base-image-id": null,
      "compartment-id": null,
      "create-image-allowed": true,
      "defined-tags": {},
      "display-name": "Windows-Server-2012-R2-Standard-Edition-VM-2019.08.21-0",
      "freeform-tags": {},
      "id": "ocid1.image.oc1.eu-frankfurt-1.aaaaaaaa6yvd5cjhq5szqxpmfoisdp7z3thpgdv2exdtmdvcgf3r25ykl36q",
      "launch-mode": "NATIVE",
      "launch-options": {
        "boot-volume-type": "PARAVIRTUALIZED",
        "firmware": "UEFI_64",
        "is-consistent-volume-naming-enabled": false,
        "is-pv-encryption-in-transit-enabled": true,
        "network-type": "VFIO",
        "remote-data-volume-type": "PARAVIRTUALIZED"
      },
      "lifecycle-state": "AVAILABLE",
      "operating-system": "Windows",
      "operating-system-version": "Server 2012 R2 Standard",
      "size-in-mbs": 262144,
      "time-created": "2019-08-21T15:50:58.128000+00:00"
    },
    {
      "agent-features": null,
      "base-image-id": null,
      "compartment-id": null,
      "create-image-allowed": true,
      "defined-tags": {},
      "display-name": "Windows-Server-2012-R2-Standard-Edition-VM-2019.06.13-0",
      "freeform-tags": {},
      "id": "ocid1.image.oc1.eu-frankfurt-1.aaaaaaaaw6lxcy6cbgzehuazfqsqhzh4qdogm2dek7b7qd3qmwwjkkys54bq",
      "launch-mode": "NATIVE",
      "launch-options": {
        "boot-volume-type": "PARAVIRTUALIZED",
        "firmware": "UEFI_64",
        "is-consistent-volume-naming-enabled": false,
        "is-pv-encryption-in-transit-enabled": true,
        "network-type": "VFIO",
        "remote-data-volume-type": "PARAVIRTUALIZED"
      },
      "lifecycle-state": "AVAILABLE",
      "operating-system": "Windows",
      "operating-system-version": "Server 2012 R2 Standard",
      "size-in-mbs": 262144,
      "time-created": "2019-06-17T22:11:20.189000+00:00"
    },
    {
      "agent-features": null,
      "base-image-id": null,
      "compartment-id": null,
      "create-image-allowed": true,
      "defined-tags": {},
      "display-name": "Windows-Server-2012-R2-Standard-Edition-VM-2019.05.15-0",
      "freeform-tags": {},
      "id": "ocid1.image.oc1.eu-frankfurt-1.aaaaaaaa3ucznvkbmbx5gjrjmobaqdkyll2h5o74h3gnptz5ye4wvofscmfq",
      "launch-mode": "NATIVE",
      "launch-options": {
        "boot-volume-type": "PARAVIRTUALIZED",
        "firmware": "UEFI_64",
        "is-consistent-volume-naming-enabled": false,
        "is-pv-encryption-in-transit-enabled": true,
        "network-type": "VFIO",
        "remote-data-volume-type": "PARAVIRTUALIZED"
      },
      "lifecycle-state": "AVAILABLE",
      "operating-system": "Windows",
      "operating-system-version": "Server 2012 R2 Standard",
      "size-in-mbs": 262144,
      "time-created": "2019-05-15T17:56:35.587000+00:00"
    },
    {
      "agent-features": null,
      "base-image-id": null,
      "compartment-id": null,
      "create-image-allowed": true,
      "defined-tags": {},
      "display-name": "Windows-Server-2012-R2-Datacenter-Edition-BM-Gen2-E2-2019.10.09-0",
      "freeform-tags": {},
      "id": "ocid1.image.oc1.eu-frankfurt-1.aaaaaaaa6j6hlo6p7hb6u7pw54u65m4fmatermnwml3vfrdngsjxl2xcni6a",
      "launch-mode": "NATIVE",
      "launch-options": {
        "boot-volume-type": "PARAVIRTUALIZED",
        "firmware": "UEFI_64",
        "is-consistent-volume-naming-enabled": false,
        "is-pv-encryption-in-transit-enabled": true,
        "network-type": "VFIO",
        "remote-data-volume-type": "PARAVIRTUALIZED"
      },
      "lifecycle-state": "AVAILABLE",
      "operating-system": "Windows",
      "operating-system-version": "Server 2012 R2 Datacenter",
      "size-in-mbs": 262144,
      "time-created": "2019-10-10T20:18:40.606000+00:00"
    },
    {
      "agent-features": null,
      "base-image-id": null,
      "compartment-id": null,
      "create-image-allowed": true,
      "defined-tags": {},
      "display-name": "Windows-Server-2012-R2-Datacenter-Edition-BM-Gen2-E2-2019.08.15-0",
      "freeform-tags": {},
      "id": "ocid1.image.oc1.eu-frankfurt-1.aaaaaaaa6guustlnqsti6pklhqvhfoxywitnt437isurk35bnblemwvqsq2a",
      "launch-mode": "NATIVE",
      "launch-options": {
        "boot-volume-type": "PARAVIRTUALIZED",
        "firmware": "UEFI_64",
        "is-consistent-volume-naming-enabled": false,
        "is-pv-encryption-in-transit-enabled": true,
        "network-type": "VFIO",
        "remote-data-volume-type": "PARAVIRTUALIZED"
      },
      "lifecycle-state": "AVAILABLE",
      "operating-system": "Windows",
      "operating-system-version": "Server 2012 R2 Datacenter",
      "size-in-mbs": 262144,
      "time-created": "2019-08-15T23:34:10.801000+00:00"
    },
    {
      "agent-features": null,
      "base-image-id": null,
      "compartment-id": null,
      "create-image-allowed": true,
      "defined-tags": {},
      "display-name": "Windows-Server-2012-R2-Datacenter-Edition-BM-Gen2-E2-2019.06.13-0",
      "freeform-tags": {},
      "id": "ocid1.image.oc1.eu-frankfurt-1.aaaaaaaa2pukhobxg5v5c2c44ffewpqzbqragto26pwe5w44wb3aoodizkya",
      "launch-mode": "NATIVE",
      "launch-options": {
        "boot-volume-type": "PARAVIRTUALIZED",
        "firmware": "UEFI_64",
        "is-consistent-volume-naming-enabled": false,
        "is-pv-encryption-in-transit-enabled": true,
        "network-type": "VFIO",
        "remote-data-volume-type": "PARAVIRTUALIZED"
      },
      "lifecycle-state": "AVAILABLE",
      "operating-system": "Windows",
      "operating-system-version": "Server 2012 R2 Datacenter",
      "size-in-mbs": 262144,
      "time-created": "2019-06-17T23:42:33.523000+00:00"
    },
    {
      "agent-features": null,
      "base-image-id": null,
      "compartment-id": null,
      "create-image-allowed": true,
      "defined-tags": {},
      "display-name": "Windows-Server-2012-R2-Datacenter-Edition-BM-Gen2-E2-2019.05.14-0",
      "freeform-tags": {},
      "id": "ocid1.image.oc1.eu-frankfurt-1.aaaaaaaargrbpibmi6h42ywsl7xulzb56aofyniejphq3jpqmpobqimauzqa",
      "launch-mode": "NATIVE",
      "launch-options": {
        "boot-volume-type": "PARAVIRTUALIZED",
        "firmware": "UEFI_64",
        "is-consistent-volume-naming-enabled": false,
        "is-pv-encryption-in-transit-enabled": true,
        "network-type": "VFIO",
        "remote-data-volume-type": "PARAVIRTUALIZED"
      },
      "lifecycle-state": "AVAILABLE",
      "operating-system": "Windows",
      "operating-system-version": "Server 2012 R2 Datacenter",
      "size-in-mbs": 262144,
      "time-created": "2019-05-15T01:21:20.707000+00:00"
    },
    {
      "agent-features": null,
      "base-image-id": null,
      "compartment-id": null,
      "create-image-allowed": true,
      "defined-tags": {},
      "display-name": "Windows-Server-2012-R2-Datacenter-Edition-BM-Gen2-E2-2018.12.13-0",
      "freeform-tags": {},
      "id": "ocid1.image.oc1.eu-frankfurt-1.aaaaaaaaymfkum6mgyfkb7yo4ejq4zwqcmpa35j3amh2fvz4i3nggpami52q",
      "launch-mode": "NATIVE",
      "launch-options": {
        "boot-volume-type": "PARAVIRTUALIZED",
        "firmware": "UEFI_64",
        "is-consistent-volume-naming-enabled": false,
        "is-pv-encryption-in-transit-enabled": true,
        "network-type": "VFIO",
        "remote-data-volume-type": "PARAVIRTUALIZED"
      },
      "lifecycle-state": "AVAILABLE",
      "operating-system": "Windows",
      "operating-system-version": "Server 2012 R2 Datacenter",
      "size-in-mbs": 262144,
      "time-created": "2018-12-13T21:42:28.659000+00:00"
    },
    {
      "agent-features": null,
      "base-image-id": null,
      "compartment-id": null,
      "create-image-allowed": true,
      "defined-tags": {},
      "display-name": "Windows-Server-2012-R2-Datacenter-Edition-BM-Gen2-DenseIO-2019.10.09-0",
      "freeform-tags": {},
      "id": "ocid1.image.oc1.eu-frankfurt-1.aaaaaaaaja43x4u27kty6ph27rfh2dan6zmrce27wicm5u5ptnjaoneqmsfa",
      "launch-mode": "NATIVE",
      "launch-options": {
        "boot-volume-type": "PARAVIRTUALIZED",
        "firmware": "UEFI_64",
        "is-consistent-volume-naming-enabled": false,
        "is-pv-encryption-in-transit-enabled": true,
        "network-type": "VFIO",
        "remote-data-volume-type": "PARAVIRTUALIZED"
      },
      "lifecycle-state": "AVAILABLE",
      "operating-system": "Windows",
      "operating-system-version": "Server 2012 R2 Datacenter",
      "size-in-mbs": 262144,
      "time-created": "2019-10-10T20:19:58.849000+00:00"
    },
    {
      "agent-features": null,
      "base-image-id": null,
      "compartment-id": null,
      "create-image-allowed": true,
      "defined-tags": {},
      "display-name": "Windows-Server-2012-R2-Datacenter-Edition-BM-Gen2-DenseIO-2019.08.23-0",
      "freeform-tags": {},
      "id": "ocid1.image.oc1.eu-frankfurt-1.aaaaaaaazgax6ywdbmuj7emqarqrdo5gijq2kjopekmkyrnpevguferk3pva",
      "launch-mode": "NATIVE",
      "launch-options": {
        "boot-volume-type": "PARAVIRTUALIZED",
        "firmware": "UEFI_64",
        "is-consistent-volume-naming-enabled": false,
        "is-pv-encryption-in-transit-enabled": true,
        "network-type": "VFIO",
        "remote-data-volume-type": "PARAVIRTUALIZED"
      },
      "lifecycle-state": "AVAILABLE",
      "operating-system": "Windows",
      "operating-system-version": "Server 2012 R2 Datacenter",
      "size-in-mbs": 262144,
      "time-created": "2019-08-23T22:37:46.382000+00:00"
    },
    {
      "agent-features": null,
      "base-image-id": null,
      "compartment-id": null,
      "create-image-allowed": true,
      "defined-tags": {},
      "display-name": "Windows-Server-2012-R2-Datacenter-Edition-BM-Gen2-DenseIO-2019.06.13-0",
      "freeform-tags": {},
      "id": "ocid1.image.oc1.eu-frankfurt-1.aaaaaaaafwbk57oscekj7ypivv6rfk6l26cycft7ci6qalejpqz4iewcosjq",
      "launch-mode": "NATIVE",
      "launch-options": {
        "boot-volume-type": "PARAVIRTUALIZED",
        "firmware": "UEFI_64",
        "is-consistent-volume-naming-enabled": false,
        "is-pv-encryption-in-transit-enabled": true,
        "network-type": "VFIO",
        "remote-data-volume-type": "PARAVIRTUALIZED"
      },
      "lifecycle-state": "AVAILABLE",
      "operating-system": "Windows",
      "operating-system-version": "Server 2012 R2 Datacenter",
      "size-in-mbs": 262144,
      "time-created": "2019-06-18T21:15:29.424000+00:00"
    },
    {
      "agent-features": null,
      "base-image-id": null,
      "compartment-id": null,
      "create-image-allowed": true,
      "defined-tags": {},
      "display-name": "Windows-Server-2012-R2-Datacenter-Edition-BM-Gen2-DenseIO-2019.05.15-0",
      "freeform-tags": {},
      "id": "ocid1.image.oc1.eu-frankfurt-1.aaaaaaaaz5ntapudsjmqb3zmks6izbtthbfqff2py7l7rztgnunsczz4ttqa",
      "launch-mode": "NATIVE",
      "launch-options": {
        "boot-volume-type": "PARAVIRTUALIZED",
        "firmware": "UEFI_64",
        "is-consistent-volume-naming-enabled": false,
        "is-pv-encryption-in-transit-enabled": true,
        "network-type": "VFIO",
        "remote-data-volume-type": "PARAVIRTUALIZED"
      },
      "lifecycle-state": "AVAILABLE",
      "operating-system": "Windows",
      "operating-system-version": "Server 2012 R2 Datacenter",
      "size-in-mbs": 262144,
      "time-created": "2019-05-15T04:58:21.534000+00:00"
    },
    {
      "agent-features": null,
      "base-image-id": null,
      "compartment-id": null,
      "create-image-allowed": true,
      "defined-tags": {},
      "display-name": "Windows-Server-2012-R2-Datacenter-Edition-BM-Gen2-2019.10.09-0",
      "freeform-tags": {},
      "id": "ocid1.image.oc1.eu-frankfurt-1.aaaaaaaa4dzzdgwey3qd4hbjzbb73eqfsykuv34nyyml655p4v2leq34tlrq",
      "launch-mode": "NATIVE",
      "launch-options": {
        "boot-volume-type": "PARAVIRTUALIZED",
        "firmware": "UEFI_64",
        "is-consistent-volume-naming-enabled": false,
        "is-pv-encryption-in-transit-enabled": true,
        "network-type": "VFIO",
        "remote-data-volume-type": "PARAVIRTUALIZED"
      },
      "lifecycle-state": "AVAILABLE",
      "operating-system": "Windows",
      "operating-system-version": "Server 2012 R2 Datacenter",
      "size-in-mbs": 262144,
      "time-created": "2019-10-11T17:28:02.087000+00:00"
    },
    {
      "agent-features": null,
      "base-image-id": null,
      "compartment-id": null,
      "create-image-allowed": true,
      "defined-tags": {},
      "display-name": "Windows-Server-2012-R2-Datacenter-Edition-BM-Gen2-2019.08.14-0",
      "freeform-tags": {},
      "id": "ocid1.image.oc1.eu-frankfurt-1.aaaaaaaabr6z6dq2wijssb2psklnc4h2p5fi3nfxujvguomxsdz7ogfndk4q",
      "launch-mode": "NATIVE",
      "launch-options": {
        "boot-volume-type": "PARAVIRTUALIZED",
        "firmware": "UEFI_64",
        "is-consistent-volume-naming-enabled": false,
        "is-pv-encryption-in-transit-enabled": true,
        "network-type": "VFIO",
        "remote-data-volume-type": "PARAVIRTUALIZED"
      },
      "lifecycle-state": "AVAILABLE",
      "operating-system": "Windows",
      "operating-system-version": "Server 2012 R2 Datacenter",
      "size-in-mbs": 262144,
      "time-created": "2019-08-21T23:47:45.503000+00:00"
    },
    {
      "agent-features": null,
      "base-image-id": null,
      "compartment-id": null,
      "create-image-allowed": true,
      "defined-tags": {},
      "display-name": "Windows-Server-2012-R2-Datacenter-Edition-BM-Gen2-2019.06.13-0",
      "freeform-tags": {},
      "id": "ocid1.image.oc1.eu-frankfurt-1.aaaaaaaar7madkfjwdkf6g6v5oq3ij4e6vbfcj2xwazapbw5m6qyaehdkaca",
      "launch-mode": "NATIVE",
      "launch-options": {
        "boot-volume-type": "PARAVIRTUALIZED",
        "firmware": "UEFI_64",
        "is-consistent-volume-naming-enabled": false,
        "is-pv-encryption-in-transit-enabled": true,
        "network-type": "VFIO",
        "remote-data-volume-type": "PARAVIRTUALIZED"
      },
      "lifecycle-state": "AVAILABLE",
      "operating-system": "Windows",
      "operating-system-version": "Server 2012 R2 Datacenter",
      "size-in-mbs": 262144,
      "time-created": "2019-06-17T23:58:50.684000+00:00"
    },
    {
      "agent-features": null,
      "base-image-id": null,
      "compartment-id": null,
      "create-image-allowed": true,
      "defined-tags": {},
      "display-name": "Windows-Server-2012-R2-Datacenter-Edition-BM-Gen2-2019.05.14-0",
      "freeform-tags": {},
      "id": "ocid1.image.oc1.eu-frankfurt-1.aaaaaaaawcr6mhwtpwyaygrggdvrtonffjqw4hhpybzaj7gmhhrwufjyzsua",
      "launch-mode": "NATIVE",
      "launch-options": {
        "boot-volume-type": "PARAVIRTUALIZED",
        "firmware": "UEFI_64",
        "is-consistent-volume-naming-enabled": false,
        "is-pv-encryption-in-transit-enabled": true,
        "network-type": "VFIO",
        "remote-data-volume-type": "PARAVIRTUALIZED"
      },
      "lifecycle-state": "AVAILABLE",
      "operating-system": "Windows",
      "operating-system-version": "Server 2012 R2 Datacenter",
      "size-in-mbs": 262144,
      "time-created": "2019-05-15T01:21:41.847000+00:00"
    },
    {
      "agent-features": null,
      "base-image-id": null,
      "compartment-id": null,
      "create-image-allowed": true,
      "defined-tags": {},
      "display-name": "Windows-Server-2012-R2-Datacenter-Edition-BM-2019.10.09-0",
      "freeform-tags": {},
      "id": "ocid1.image.oc1.eu-frankfurt-1.aaaaaaaaoi6mfmyiljsxze5mtkrxyr3qyaveeguyoirbj5ir6hgjf36mq5zq",
      "launch-mode": "NATIVE",
      "launch-options": {
        "boot-volume-type": "PARAVIRTUALIZED",
        "firmware": "UEFI_64",
        "is-consistent-volume-naming-enabled": false,
        "is-pv-encryption-in-transit-enabled": true,
        "network-type": "VFIO",
        "remote-data-volume-type": "PARAVIRTUALIZED"
      },
      "lifecycle-state": "AVAILABLE",
      "operating-system": "Windows",
      "operating-system-version": "Server 2012 R2 Datacenter",
      "size-in-mbs": 262144,
      "time-created": "2019-10-15T00:47:41.786000+00:00"
    },
    {
      "agent-features": null,
      "base-image-id": null,
      "compartment-id": null,
      "create-image-allowed": true,
      "defined-tags": {},
      "display-name": "Windows-Server-2012-R2-Datacenter-Edition-BM-2019.09.05-0",
      "freeform-tags": {},
      "id": "ocid1.image.oc1.eu-frankfurt-1.aaaaaaaarpkg4dsk2plueqodf7eiii7ojaofhvtugbttkpjqupbs4rzd4tyq",
      "launch-mode": "NATIVE",
      "launch-options": {
        "boot-volume-type": "PARAVIRTUALIZED",
        "firmware": "UEFI_64",
        "is-consistent-volume-naming-enabled": false,
        "is-pv-encryption-in-transit-enabled": true,
        "network-type": "VFIO",
        "remote-data-volume-type": "PARAVIRTUALIZED"
      },
      "lifecycle-state": "AVAILABLE",
      "operating-system": "Windows",
      "operating-system-version": "Server 2012 R2 Datacenter",
      "size-in-mbs": 262144,
      "time-created": "2019-09-06T03:09:40.022000+00:00"
    },
    {
      "agent-features": null,
      "base-image-id": null,
      "compartment-id": null,
      "create-image-allowed": true,
      "defined-tags": {},
      "display-name": "Windows-Server-2012-R2-Datacenter-Edition-BM-2019.06.17-0",
      "freeform-tags": {},
      "id": "ocid1.image.oc1.eu-frankfurt-1.aaaaaaaals2tkyyqupwjl6mzz4ovppioxr6dwkf3k6qwux34xd26pb2fe6hq",
      "launch-mode": "NATIVE",
      "launch-options": {
        "boot-volume-type": "PARAVIRTUALIZED",
        "firmware": "UEFI_64",
        "is-consistent-volume-naming-enabled": false,
        "is-pv-encryption-in-transit-enabled": true,
        "network-type": "VFIO",
        "remote-data-volume-type": "PARAVIRTUALIZED"
      },
      "lifecycle-state": "AVAILABLE",
      "operating-system": "Windows",
      "operating-system-version": "Server 2012 R2 Datacenter",
      "size-in-mbs": 262144,
      "time-created": "2019-06-19T18:02:34.946000+00:00"
    },
    {
      "agent-features": null,
      "base-image-id": null,
      "compartment-id": null,
      "create-image-allowed": true,
      "defined-tags": {},
      "display-name": "Windows-Server-2012-R2-Datacenter-Edition-BM-2019.01.09-0",
      "freeform-tags": {},
      "id": "ocid1.image.oc1.eu-frankfurt-1.aaaaaaaax7zdynzomhs3f6pepmyc3khnr2k46cs5va2w7eguguyw4wmlwafa",
      "launch-mode": "NATIVE",
      "launch-options": {
        "boot-volume-type": "PARAVIRTUALIZED",
        "firmware": "UEFI_64",
        "is-consistent-volume-naming-enabled": false,
        "is-pv-encryption-in-transit-enabled": true,
        "network-type": "VFIO",
        "remote-data-volume-type": "PARAVIRTUALIZED"
      },
      "lifecycle-state": "AVAILABLE",
      "operating-system": "Windows",
      "operating-system-version": "Server 2012 R2 Datacenter",
      "size-in-mbs": 262144,
      "time-created": "2019-01-12T00:15:57.827000+00:00"
    },
    {
      "agent-features": null,
      "base-image-id": null,
      "compartment-id": null,
      "create-image-allowed": true,
      "defined-tags": {},
      "display-name": "Windows-Server-2012-R2-Datacenter-Edition-BM-2018.11.16-0",
      "freeform-tags": {},
      "id": "ocid1.image.oc1.eu-frankfurt-1.aaaaaaaal77ivptp6a7x37nzxljmyxjkeiiz3ciapzcvk7s57viaqzklmyeq",
      "launch-mode": "NATIVE",
      "launch-options": {
        "boot-volume-type": "PARAVIRTUALIZED",
        "firmware": "UEFI_64",
        "is-consistent-volume-naming-enabled": false,
        "is-pv-encryption-in-transit-enabled": true,
        "network-type": "VFIO",
        "remote-data-volume-type": "PARAVIRTUALIZED"
      },
      "lifecycle-state": "AVAILABLE",
      "operating-system": "Windows",
      "operating-system-version": "Server 2012 R2 Datacenter",
      "size-in-mbs": 262144,
      "time-created": "2018-11-20T18:41:04.256000+00:00"
    },
    {
      "agent-features": null,
      "base-image-id": null,
      "compartment-id": null,
      "create-image-allowed": true,
      "defined-tags": {},
      "display-name": "Windows-Server-2008-R2-Enterprise-Edition-VM-Gen2-2019.10.09-0",
      "freeform-tags": {},
      "id": "ocid1.image.oc1.eu-frankfurt-1.aaaaaaaahuxeugf2uiv43pbac2cznxco2drzzqc23eg2o7kdiqbzowwqc3ta",
      "launch-mode": "NATIVE",
      "launch-options": {
        "boot-volume-type": "PARAVIRTUALIZED",
        "firmware": "UEFI_64",
        "is-consistent-volume-naming-enabled": false,
        "is-pv-encryption-in-transit-enabled": true,
        "network-type": "VFIO",
        "remote-data-volume-type": "PARAVIRTUALIZED"
      },
      "lifecycle-state": "AVAILABLE",
      "operating-system": "Windows",
      "operating-system-version": "Server 2008 R2",
      "size-in-mbs": 262144,
      "time-created": "2019-10-10T00:47:11.912000+00:00"
    },
    {
      "agent-features": null,
      "base-image-id": null,
      "compartment-id": null,
      "create-image-allowed": true,
      "defined-tags": {},
      "display-name": "Windows-Server-2008-R2-Enterprise-Edition-VM-Gen2-2019.09.27-0",
      "freeform-tags": {},
      "id": "ocid1.image.oc1.eu-frankfurt-1.aaaaaaaa62de7ncq2y3gootbuyattcyfq5xqp5uecmzqfiirzzq5mce2wtaq",
      "launch-mode": "NATIVE",
      "launch-options": {
        "boot-volume-type": "PARAVIRTUALIZED",
        "firmware": "UEFI_64",
        "is-consistent-volume-naming-enabled": false,
        "is-pv-encryption-in-transit-enabled": true,
        "network-type": "VFIO",
        "remote-data-volume-type": "PARAVIRTUALIZED"
      },
      "lifecycle-state": "AVAILABLE",
      "operating-system": "Windows",
      "operating-system-version": "Server 2008 R2",
      "size-in-mbs": 262144,
      "time-created": "2019-09-30T22:45:45.597000+00:00"
    },
    {
      "agent-features": null,
      "base-image-id": null,
      "compartment-id": null,
      "create-image-allowed": true,
      "defined-tags": {},
      "display-name": "Windows-Server-2008-R2-Enterprise-Edition-VM-Gen2-2019.08.15-0",
      "freeform-tags": {},
      "id": "ocid1.image.oc1.eu-frankfurt-1.aaaaaaaapuddwzwm7inihi3yilroxzonhlayepajdlgx7cqgrgs3mzvzcwba",
      "launch-mode": "NATIVE",
      "launch-options": {
        "boot-volume-type": "PARAVIRTUALIZED",
        "firmware": "UEFI_64",
        "is-consistent-volume-naming-enabled": false,
        "is-pv-encryption-in-transit-enabled": true,
        "network-type": "VFIO",
        "remote-data-volume-type": "PARAVIRTUALIZED"
      },
      "lifecycle-state": "AVAILABLE",
      "operating-system": "Windows",
      "operating-system-version": "Server 2008 R2",
      "size-in-mbs": 262144,
      "time-created": "2019-08-15T05:44:26.037000+00:00"
    },
    {
      "agent-features": null,
      "base-image-id": null,
      "compartment-id": null,
      "create-image-allowed": true,
      "defined-tags": {},
      "display-name": "Windows-Server-2008-R2-Enterprise-Edition-VM-2019.10.09-0",
      "freeform-tags": {},
      "id": "ocid1.image.oc1.eu-frankfurt-1.aaaaaaaao6o35tillhvxk2ievufmlnt4mfne4y3u5d4ofwj5icv4hqser7pq",
      "launch-mode": "NATIVE",
      "launch-options": {
        "boot-volume-type": "PARAVIRTUALIZED",
        "firmware": "UEFI_64",
        "is-consistent-volume-naming-enabled": false,
        "is-pv-encryption-in-transit-enabled": true,
        "network-type": "VFIO",
        "remote-data-volume-type": "PARAVIRTUALIZED"
      },
      "lifecycle-state": "AVAILABLE",
      "operating-system": "Windows",
      "operating-system-version": "Server 2008 R2",
      "size-in-mbs": 262144,
      "time-created": "2019-10-10T21:39:45.904000+00:00"
    },
    {
      "agent-features": null,
      "base-image-id": null,
      "compartment-id": null,
      "create-image-allowed": true,
      "defined-tags": {},
      "display-name": "Windows-Server-2008-R2-Enterprise-Edition-VM-2019.09.27-0",
      "freeform-tags": {},
      "id": "ocid1.image.oc1.eu-frankfurt-1.aaaaaaaaoxsujejv4tfxegijqmqtozfe3ke756us2xlsiqpet7ezr4vmpblq",
      "launch-mode": "NATIVE",
      "launch-options": {
        "boot-volume-type": "PARAVIRTUALIZED",
        "firmware": "UEFI_64",
        "is-consistent-volume-naming-enabled": false,
        "is-pv-encryption-in-transit-enabled": true,
        "network-type": "VFIO",
        "remote-data-volume-type": "PARAVIRTUALIZED"
      },
      "lifecycle-state": "AVAILABLE",
      "operating-system": "Windows",
      "operating-system-version": "Server 2008 R2",
      "size-in-mbs": 262144,
      "time-created": "2019-09-30T21:00:03.227000+00:00"
    },
    {
      "agent-features": null,
      "base-image-id": null,
      "compartment-id": null,
      "create-image-allowed": true,
      "defined-tags": {},
      "display-name": "Windows-Server-2008-R2-Enterprise-Edition-VM-2019.08.14-0",
      "freeform-tags": {},
      "id": "ocid1.image.oc1.eu-frankfurt-1.aaaaaaaau322jzrk7a5bhonfva6an5zuuszoht7ov2j25qzg3jqw6rucgw2q",
      "launch-mode": "NATIVE",
      "launch-options": {
        "boot-volume-type": "PARAVIRTUALIZED",
        "firmware": "UEFI_64",
        "is-consistent-volume-naming-enabled": false,
        "is-pv-encryption-in-transit-enabled": true,
        "network-type": "VFIO",
        "remote-data-volume-type": "PARAVIRTUALIZED"
      },
      "lifecycle-state": "AVAILABLE",
      "operating-system": "Windows",
      "operating-system-version": "Server 2008 R2",
      "size-in-mbs": 262144,
      "time-created": "2019-08-15T04:57:02.849000+00:00"
    },
    {
      "agent-features": null,
      "base-image-id": null,
      "compartment-id": null,
      "create-image-allowed": true,
      "defined-tags": {},
      "display-name": "Oracle-Linux-7.7-Gen2-GPU-2019.09.25-0",
      "freeform-tags": {},
      "id": "ocid1.image.oc1.eu-frankfurt-1.aaaaaaaahwgb2adnqvfwhjgqgymx4gq5ecxeqqxr7oy5gzbc35jygm3tpz2a",
      "launch-mode": "NATIVE",
      "launch-options": {
        "boot-volume-type": "PARAVIRTUALIZED",
        "firmware": "UEFI_64",
        "is-consistent-volume-naming-enabled": true,
        "is-pv-encryption-in-transit-enabled": true,
        "network-type": "PARAVIRTUALIZED",
        "remote-data-volume-type": "PARAVIRTUALIZED"
      },
      "lifecycle-state": "AVAILABLE",
      "operating-system": "Oracle Linux",
      "operating-system-version": "7.7",
      "size-in-mbs": 47694,
      "time-created": "2019-09-26T21:27:48.063000+00:00"
    },
    {
      "agent-features": null,
      "base-image-id": null,
      "compartment-id": null,
      "create-image-allowed": true,
      "defined-tags": {},
      "display-name": "Oracle-Linux-7.7-Gen2-GPU-2019.08.28-0",
      "freeform-tags": {},
      "id": "ocid1.image.oc1.eu-frankfurt-1.aaaaaaaaiaft5bon64aq74zejtshgkymq63t2onjci4gizf6o72iv7dfdixq",
      "launch-mode": "NATIVE",
      "launch-options": {
        "boot-volume-type": "PARAVIRTUALIZED",
        "firmware": "UEFI_64",
        "is-consistent-volume-naming-enabled": true,
        "is-pv-encryption-in-transit-enabled": true,
        "network-type": "PARAVIRTUALIZED",
        "remote-data-volume-type": "PARAVIRTUALIZED"
      },
      "lifecycle-state": "AVAILABLE",
      "operating-system": "Oracle Linux",
      "operating-system-version": "7.7",
      "size-in-mbs": 47694,
      "time-created": "2019-08-30T19:30:23.379000+00:00"
    },
    {
      "agent-features": null,
      "base-image-id": null,
      "compartment-id": null,
      "create-image-allowed": true,
      "defined-tags": {},
      "display-name": "Oracle-Linux-7.7-2019.09.25-0",
      "freeform-tags": {},
      "id": "ocid1.image.oc1.eu-frankfurt-1.aaaaaaaajqghpxnszpnghz3um66jywaw5q3pudfw5qwwkyu24ef7lcsyjhsq",
      "launch-mode": "NATIVE",
      "launch-options": {
        "boot-volume-type": "PARAVIRTUALIZED",
        "firmware": "UEFI_64",
        "is-consistent-volume-naming-enabled": true,
        "is-pv-encryption-in-transit-enabled": true,
        "network-type": "PARAVIRTUALIZED",
        "remote-data-volume-type": "PARAVIRTUALIZED"
      },
      "lifecycle-state": "AVAILABLE",
      "operating-system": "Oracle Linux",
      "operating-system-version": "7.7",
      "size-in-mbs": 47694,
      "time-created": "2019-09-26T21:55:21.930000+00:00"
    },
    {
      "agent-features": null,
      "base-image-id": null,
      "compartment-id": null,
      "create-image-allowed": true,
      "defined-tags": {},
      "display-name": "Oracle-Linux-7.7-2019.08.28-0",
      "freeform-tags": {},
      "id": "ocid1.image.oc1.eu-frankfurt-1.aaaaaaaa7gj6uot6tz6t34qjzvkldxtwse7gr5m7xvnh6xfm53ddxp3w37ja",
      "launch-mode": "NATIVE",
      "launch-options": {
        "boot-volume-type": "PARAVIRTUALIZED",
        "firmware": "UEFI_64",
        "is-consistent-volume-naming-enabled": true,
        "is-pv-encryption-in-transit-enabled": true,
        "network-type": "PARAVIRTUALIZED",
        "remote-data-volume-type": "PARAVIRTUALIZED"
      },
      "lifecycle-state": "AVAILABLE",
      "operating-system": "Oracle Linux",
      "operating-system-version": "7.7",
      "size-in-mbs": 47694,
      "time-created": "2019-08-29T00:16:00.863000+00:00"
    },
    {
      "agent-features": null,
      "base-image-id": null,
      "compartment-id": null,
      "create-image-allowed": true,
      "defined-tags": {},
      "display-name": "Oracle-Linux-7.6-Gen2-GPU-2019.08.06-0",
      "freeform-tags": {},
      "id": "ocid1.image.oc1.eu-frankfurt-1.aaaaaaaaukviflrmb3sjwphzemh47yrbspfhiifagca4nm7lxg4p5hndaqiq",
      "launch-mode": "NATIVE",
      "launch-options": {
        "boot-volume-type": "PARAVIRTUALIZED",
        "firmware": "UEFI_64",
        "is-consistent-volume-naming-enabled": true,
        "is-pv-encryption-in-transit-enabled": true,
        "network-type": "PARAVIRTUALIZED",
        "remote-data-volume-type": "PARAVIRTUALIZED"
      },
      "lifecycle-state": "AVAILABLE",
      "operating-system": "Oracle Linux",
      "operating-system-version": "7.6",
      "size-in-mbs": 47694,
      "time-created": "2019-08-04T21:42:45.551000+00:00"
    },
    {
      "agent-features": null,
      "base-image-id": null,
      "compartment-id": null,
      "create-image-allowed": true,
      "defined-tags": {},
      "display-name": "Oracle-Linux-7.6-Gen2-GPU-2019.07.15-0",
      "freeform-tags": {},
      "id": "ocid1.image.oc1.eu-frankfurt-1.aaaaaaaau6iig4zgkrvxn3leeeb6khbcsgdu3vksqjwhfgiohefldqfwd7zq",
      "launch-mode": "NATIVE",
      "launch-options": {
        "boot-volume-type": "PARAVIRTUALIZED",
        "firmware": "UEFI_64",
        "is-consistent-volume-naming-enabled": true,
        "is-pv-encryption-in-transit-enabled": true,
        "network-type": "PARAVIRTUALIZED",
        "remote-data-volume-type": "PARAVIRTUALIZED"
      },
      "lifecycle-state": "AVAILABLE",
      "operating-system": "Oracle Linux",
      "operating-system-version": "7.6",
      "size-in-mbs": 47694,
      "time-created": "2019-07-15T18:55:39.838000+00:00"
    },
    {
      "agent-features": null,
      "base-image-id": null,
      "compartment-id": null,
      "create-image-allowed": true,
      "defined-tags": {},
      "display-name": "Oracle-Linux-7.6-2019.08.02-0",
      "freeform-tags": {},
      "id": "ocid1.image.oc1.eu-frankfurt-1.aaaaaaaax3xjmpwufw6tucuoyuenletg74sdsj5f2gzsvlv4mqbbgeokqzsq",
      "launch-mode": "NATIVE",
      "launch-options": {
        "boot-volume-type": "PARAVIRTUALIZED",
        "firmware": "UEFI_64",
        "is-consistent-volume-naming-enabled": true,
        "is-pv-encryption-in-transit-enabled": true,
        "network-type": "PARAVIRTUALIZED",
        "remote-data-volume-type": "PARAVIRTUALIZED"
      },
      "lifecycle-state": "AVAILABLE",
      "operating-system": "Oracle Linux",
      "operating-system-version": "7.6",
      "size-in-mbs": 47694,
      "time-created": "2019-08-04T18:31:26.585000+00:00"
    },
    {
      "agent-features": null,
      "base-image-id": null,
      "compartment-id": null,
      "create-image-allowed": true,
      "defined-tags": {},
      "display-name": "Oracle-Linux-7.6-2019.07.15-0",
      "freeform-tags": {},
      "id": "ocid1.image.oc1.eu-frankfurt-1.aaaaaaaakuepu6owftdo3qq2rftcoiwdhyj5jjxfdws6gxnv5gpdxpvtjnrq",
      "launch-mode": "NATIVE",
      "launch-options": {
        "boot-volume-type": "PARAVIRTUALIZED",
        "firmware": "UEFI_64",
        "is-consistent-volume-naming-enabled": true,
        "is-pv-encryption-in-transit-enabled": true,
        "network-type": "PARAVIRTUALIZED",
        "remote-data-volume-type": "PARAVIRTUALIZED"
      },
      "lifecycle-state": "AVAILABLE",
      "operating-system": "Oracle Linux",
      "operating-system-version": "7.6",
      "size-in-mbs": 47694,
      "time-created": "2019-07-15T18:53:29.532000+00:00"
    },
    {
      "agent-features": null,
      "base-image-id": null,
      "compartment-id": null,
      "create-image-allowed": true,
      "defined-tags": {},
      "display-name": "Oracle-Linux-6.10-2019.09.25-0",
      "freeform-tags": {},
      "id": "ocid1.image.oc1.eu-frankfurt-1.aaaaaaaate7vhjyimwcoai3r53uds23257hdw2mfj36iqtqmi3jeubompd4a",
      "launch-mode": "NATIVE",
      "launch-options": {
        "boot-volume-type": "PARAVIRTUALIZED",
        "firmware": "UEFI_64",
        "is-consistent-volume-naming-enabled": true,
        "is-pv-encryption-in-transit-enabled": true,
        "network-type": "PARAVIRTUALIZED",
        "remote-data-volume-type": "PARAVIRTUALIZED"
      },
      "lifecycle-state": "AVAILABLE",
      "operating-system": "Oracle Linux",
      "operating-system-version": "6.10",
      "size-in-mbs": 47694,
      "time-created": "2019-09-26T19:35:25.043000+00:00"
    },
    {
      "agent-features": null,
      "base-image-id": null,
      "compartment-id": null,
      "create-image-allowed": true,
      "defined-tags": {},
      "display-name": "Oracle-Linux-6.10-2019.08.30-0",
      "freeform-tags": {},
      "id": "ocid1.image.oc1.eu-frankfurt-1.aaaaaaaawlfyj3knijnfrgpeqegz2afjnnelxeywbjsmcesbf7d2iawszsxa",
      "launch-mode": "NATIVE",
      "launch-options": {
        "boot-volume-type": "PARAVIRTUALIZED",
        "firmware": "UEFI_64",
        "is-consistent-volume-naming-enabled": true,
        "is-pv-encryption-in-transit-enabled": true,
        "network-type": "PARAVIRTUALIZED",
        "remote-data-volume-type": "PARAVIRTUALIZED"
      },
      "lifecycle-state": "AVAILABLE",
      "operating-system": "Oracle Linux",
      "operating-system-version": "6.10",
      "size-in-mbs": 47694,
      "time-created": "2019-08-30T23:41:53.593000+00:00"
    },
    {
      "agent-features": null,
      "base-image-id": null,
      "compartment-id": null,
      "create-image-allowed": true,
      "defined-tags": {},
      "display-name": "Oracle-Linux-6.10-2019.08.02-0",
      "freeform-tags": {},
      "id": "ocid1.image.oc1.eu-frankfurt-1.aaaaaaaas5n4xc7zfrzg42pq7yvlkhimmsug4p27uylpgi2l5ja2o3hhcyuq",
      "launch-mode": "NATIVE",
      "launch-options": {
        "boot-volume-type": "PARAVIRTUALIZED",
        "firmware": "UEFI_64",
        "is-consistent-volume-naming-enabled": true,
        "is-pv-encryption-in-transit-enabled": true,
        "network-type": "PARAVIRTUALIZED",
        "remote-data-volume-type": "PARAVIRTUALIZED"
      },
      "lifecycle-state": "AVAILABLE",
      "operating-system": "Oracle Linux",
      "operating-system-version": "6.10",
      "size-in-mbs": 47694,
      "time-created": "2019-08-04T18:29:52.822000+00:00"
    },
    {
      "agent-features": null,
      "base-image-id": null,
      "compartment-id": null,
      "create-image-allowed": true,
      "defined-tags": {},
      "display-name": "Oracle-Linux-6.10-2019.07.15-0",
      "freeform-tags": {},
      "id": "ocid1.image.oc1.eu-frankfurt-1.aaaaaaaanwrc2crha7mxyzmdsa5huazzk6ivfmehqiotl52mtgbz2vhcvcna",
      "launch-mode": "NATIVE",
      "launch-options": {
        "boot-volume-type": "PARAVIRTUALIZED",
        "firmware": "UEFI_64",
        "is-consistent-volume-naming-enabled": true,
        "is-pv-encryption-in-transit-enabled": true,
        "network-type": "PARAVIRTUALIZED",
        "remote-data-volume-type": "PARAVIRTUALIZED"
      },
      "lifecycle-state": "AVAILABLE",
      "operating-system": "Oracle Linux",
      "operating-system-version": "6.10",
      "size-in-mbs": 47694,
      "time-created": "2019-07-15T18:49:33.434000+00:00"
    },
    {
      "agent-features": null,
      "base-image-id": null,
      "compartment-id": null,
      "create-image-allowed": true,
      "defined-tags": {},
      "display-name": "CentOS-7-PV-2019.09.30-0",
      "freeform-tags": {},
      "id": "ocid1.image.oc1.eu-frankfurt-1.aaaaaaaarduo7uxdk32yvgaramdscwpyoa4ra2f5msfrnx6rwwhgsd6ndvba",
      "launch-mode": "PARAVIRTUALIZED",
      "launch-options": {
        "boot-volume-type": "PARAVIRTUALIZED",
        "firmware": "BIOS",
        "is-consistent-volume-naming-enabled": true,
        "is-pv-encryption-in-transit-enabled": true,
        "network-type": "PARAVIRTUALIZED",
        "remote-data-volume-type": "PARAVIRTUALIZED"
      },
      "lifecycle-state": "AVAILABLE",
      "operating-system": "CentOS",
      "operating-system-version": "7",
      "size-in-mbs": 47694,
      "time-created": "2019-10-03T19:23:10.196000+00:00"
    },
    {
      "agent-features": null,
      "base-image-id": null,
      "compartment-id": null,
      "create-image-allowed": true,
      "defined-tags": {},
      "display-name": "CentOS-7-PV-2019.08.20-0",
      "freeform-tags": {},
      "id": "ocid1.image.oc1.eu-frankfurt-1.aaaaaaaaowda4m3rgjcustb4xeg3m7pkkm5a7sbngur6qqozszfil3snoqza",
      "launch-mode": "PARAVIRTUALIZED",
      "launch-options": {
        "boot-volume-type": "PARAVIRTUALIZED",
        "firmware": "BIOS",
        "is-consistent-volume-naming-enabled": true,
        "is-pv-encryption-in-transit-enabled": true,
        "network-type": "PARAVIRTUALIZED",
        "remote-data-volume-type": "PARAVIRTUALIZED"
      },
      "lifecycle-state": "AVAILABLE",
      "operating-system": "CentOS",
      "operating-system-version": "7",
      "size-in-mbs": 47694,
      "time-created": "2019-09-11T17:20:22.305000+00:00"
    },
    {
      "agent-features": null,
      "base-image-id": null,
      "compartment-id": null,
      "create-image-allowed": true,
      "defined-tags": {},
      "display-name": "CentOS-7-2019.08.20-0",
      "freeform-tags": {},
      "id": "ocid1.image.oc1.eu-frankfurt-1.aaaaaaaawejnjwwnzapqukqudpczm4pwtpcsjhohl7qcqa5vzd3gxwmqiq3q",
      "launch-mode": "NATIVE",
      "launch-options": {
        "boot-volume-type": "PARAVIRTUALIZED",
        "firmware": "UEFI_64",
        "is-consistent-volume-naming-enabled": true,
        "is-pv-encryption-in-transit-enabled": true,
        "network-type": "PARAVIRTUALIZED",
        "remote-data-volume-type": "PARAVIRTUALIZED"
      },
      "lifecycle-state": "AVAILABLE",
      "operating-system": "CentOS",
      "operating-system-version": "7",
      "size-in-mbs": 47694,
      "time-created": "2019-08-23T23:57:10.376000+00:00"
    },
    {
      "agent-features": null,
      "base-image-id": null,
      "compartment-id": null,
      "create-image-allowed": true,
      "defined-tags": {},
      "display-name": "CentOS-7-2019.07.18-0",
      "freeform-tags": {},
      "id": "ocid1.image.oc1.eu-frankfurt-1.aaaaaaaassfjfflfwty6c24gxoou224djh7rfm3cdnnq5v2jcx6eslwx4fpa",
      "launch-mode": "NATIVE",
      "launch-options": {
        "boot-volume-type": "PARAVIRTUALIZED",
        "firmware": "UEFI_64",
        "is-consistent-volume-naming-enabled": true,
        "is-pv-encryption-in-transit-enabled": true,
        "network-type": "PARAVIRTUALIZED",
        "remote-data-volume-type": "PARAVIRTUALIZED"
      },
      "lifecycle-state": "AVAILABLE",
      "operating-system": "CentOS",
      "operating-system-version": "7",
      "size-in-mbs": 47694,
      "time-created": "2019-07-18T22:06:50.356000+00:00"
    },
    {
      "agent-features": null,
      "base-image-id": null,
      "compartment-id": null,
      "create-image-allowed": true,
      "defined-tags": {},
      "display-name": "CentOS-7-2019.06.19-0",
      "freeform-tags": {},
      "id": "ocid1.image.oc1.eu-frankfurt-1.aaaaaaaaxczipclugofaltvodekopeto6xpbq7e7dk4m7so2zk3qi7nsvkyq",
      "launch-mode": "NATIVE",
      "launch-options": {
        "boot-volume-type": "PARAVIRTUALIZED",
        "firmware": "UEFI_64",
        "is-consistent-volume-naming-enabled": true,
        "is-pv-encryption-in-transit-enabled": true,
        "network-type": "PARAVIRTUALIZED",
        "remote-data-volume-type": "PARAVIRTUALIZED"
      },
      "lifecycle-state": "AVAILABLE",
      "operating-system": "CentOS",
      "operating-system-version": "7",
      "size-in-mbs": 47694,
      "time-created": "2019-06-20T18:05:30.757000+00:00"
    },
    {
      "agent-features": null,
      "base-image-id": null,
      "compartment-id": null,
      "create-image-allowed": true,
      "defined-tags": {},
      "display-name": "CentOS-6.10-2019.10.11-0",
      "freeform-tags": {},
      "id": "ocid1.image.oc1.eu-frankfurt-1.aaaaaaaa4ixic2hx4xsopejukl4nqozfbpgotkacb2bvgtur7bxnv4n2zgfa",
      "launch-mode": "NATIVE",
      "launch-options": {
        "boot-volume-type": "PARAVIRTUALIZED",
        "firmware": "UEFI_64",
        "is-consistent-volume-naming-enabled": true,
        "is-pv-encryption-in-transit-enabled": true,
        "network-type": "PARAVIRTUALIZED",
        "remote-data-volume-type": "PARAVIRTUALIZED"
      },
      "lifecycle-state": "AVAILABLE",
      "operating-system": "CentOS",
      "operating-system-version": "6.10",
      "size-in-mbs": 47694,
      "time-created": "2019-10-14T12:33:39.827000+00:00"
    },
    {
      "agent-features": null,
      "base-image-id": null,
      "compartment-id": null,
      "create-image-allowed": true,
      "defined-tags": {},
      "display-name": "CentOS-6.10-2019.08.21-0",
      "freeform-tags": {},
      "id": "ocid1.image.oc1.eu-frankfurt-1.aaaaaaaabfbku3evwzk6jhr5nx5aihz6vnccihmdlq7pjty73fdpgwspm6ea",
      "launch-mode": "NATIVE",
      "launch-options": {
        "boot-volume-type": "PARAVIRTUALIZED",
        "firmware": "UEFI_64",
        "is-consistent-volume-naming-enabled": true,
        "is-pv-encryption-in-transit-enabled": true,
        "network-type": "PARAVIRTUALIZED",
        "remote-data-volume-type": "PARAVIRTUALIZED"
      },
      "lifecycle-state": "AVAILABLE",
      "operating-system": "CentOS",
      "operating-system-version": "6.10",
      "size-in-mbs": 47694,
      "time-created": "2019-08-22T22:41:42.740000+00:00"
    },
    {
      "agent-features": null,
      "base-image-id": null,
      "compartment-id": null,
      "create-image-allowed": true,
      "defined-tags": {},
      "display-name": "CentOS-6.10-2019.07.17-0",
      "freeform-tags": {},
      "id": "ocid1.image.oc1.eu-frankfurt-1.aaaaaaaau5e74b5had6rzekxrlm4q35xunu5c6gbmqffxxogbuasomnzfqma",
      "launch-mode": "NATIVE",
      "launch-options": {
        "boot-volume-type": "PARAVIRTUALIZED",
        "firmware": "UEFI_64",
        "is-consistent-volume-naming-enabled": true,
        "is-pv-encryption-in-transit-enabled": true,
        "network-type": "PARAVIRTUALIZED",
        "remote-data-volume-type": "PARAVIRTUALIZED"
      },
      "lifecycle-state": "AVAILABLE",
      "operating-system": "CentOS",
      "operating-system-version": "6.10",
      "size-in-mbs": 47694,
      "time-created": "2019-07-18T16:03:35.217000+00:00"
    },
    {
      "agent-features": null,
      "base-image-id": null,
      "compartment-id": null,
      "create-image-allowed": true,
      "defined-tags": {},
      "display-name": "Canonical-Ubuntu-18.04-Minimal-2019.10.10-0",
      "freeform-tags": {},
      "id": "ocid1.image.oc1.eu-frankfurt-1.aaaaaaaanxqltdugy5sh3fxdxxni4zjl62rizzh6vjokksj3bkra434q6mfq",
      "launch-mode": "NATIVE",
      "launch-options": {
        "boot-volume-type": "PARAVIRTUALIZED",
        "firmware": "UEFI_64",
        "is-consistent-volume-naming-enabled": true,
        "is-pv-encryption-in-transit-enabled": true,
        "network-type": "PARAVIRTUALIZED",
        "remote-data-volume-type": "PARAVIRTUALIZED"
      },
      "lifecycle-state": "AVAILABLE",
      "operating-system": "Canonical Ubuntu",
      "operating-system-version": "18.04 Minimal",
      "size-in-mbs": 47694,
      "time-created": "2019-10-13T00:32:29.345000+00:00"
    },
    {
      "agent-features": null,
      "base-image-id": null,
      "compartment-id": null,
      "create-image-allowed": true,
      "defined-tags": {},
      "display-name": "Canonical-Ubuntu-18.04-Minimal-2019.09.21-0",
      "freeform-tags": {},
      "id": "ocid1.image.oc1.eu-frankfurt-1.aaaaaaaababsmymwjqe64jf7bfgqtdbv2dyjowygke5nve2e6odrk6vg2q5a",
      "launch-mode": "NATIVE",
      "launch-options": {
        "boot-volume-type": "PARAVIRTUALIZED",
        "firmware": "UEFI_64",
        "is-consistent-volume-naming-enabled": true,
        "is-pv-encryption-in-transit-enabled": true,
        "network-type": "PARAVIRTUALIZED",
        "remote-data-volume-type": "PARAVIRTUALIZED"
      },
      "lifecycle-state": "AVAILABLE",
      "operating-system": "Canonical Ubuntu",
      "operating-system-version": "18.04 Minimal",
      "size-in-mbs": 47694,
      "time-created": "2019-09-23T20:16:18.469000+00:00"
    },
    {
      "agent-features": null,
      "base-image-id": null,
      "compartment-id": null,
      "create-image-allowed": true,
      "defined-tags": {},
      "display-name": "Canonical-Ubuntu-18.04-Minimal-2019.08.14-0",
      "freeform-tags": {},
      "id": "ocid1.image.oc1.eu-frankfurt-1.aaaaaaaah2bq5ex7rwq3b23xqwxuf4xey7623hbrnidn4gf3qglslcf2ghnq",
      "launch-mode": "NATIVE",
      "launch-options": {
        "boot-volume-type": "PARAVIRTUALIZED",
        "firmware": "UEFI_64",
        "is-consistent-volume-naming-enabled": true,
        "is-pv-encryption-in-transit-enabled": true,
        "network-type": "PARAVIRTUALIZED",
        "remote-data-volume-type": "PARAVIRTUALIZED"
      },
      "lifecycle-state": "AVAILABLE",
      "operating-system": "Canonical Ubuntu",
      "operating-system-version": "18.04 Minimal",
      "size-in-mbs": 47694,
      "time-created": "2019-08-15T12:49:09.476000+00:00"
    },
    {
      "agent-features": null,
      "base-image-id": null,
      "compartment-id": null,
      "create-image-allowed": true,
      "defined-tags": {},
      "display-name": "Canonical-Ubuntu-18.04-2019.10.10-0",
      "freeform-tags": {},
      "id": "ocid1.image.oc1.eu-frankfurt-1.aaaaaaaafqssiu4u2ph5dvotp6ane7uextzfxxirhgpn5xunzjaqobnecowa",
      "launch-mode": "NATIVE",
      "launch-options": {
        "boot-volume-type": "PARAVIRTUALIZED",
        "firmware": "UEFI_64",
        "is-consistent-volume-naming-enabled": true,
        "is-pv-encryption-in-transit-enabled": true,
        "network-type": "PARAVIRTUALIZED",
        "remote-data-volume-type": "PARAVIRTUALIZED"
      },
      "lifecycle-state": "AVAILABLE",
      "operating-system": "Canonical Ubuntu",
      "operating-system-version": "18.04",
      "size-in-mbs": 47694,
      "time-created": "2019-10-11T20:19:28.573000+00:00"
    },
    {
      "agent-features": null,
      "base-image-id": null,
      "compartment-id": null,
      "create-image-allowed": true,
      "defined-tags": {},
      "display-name": "Canonical-Ubuntu-18.04-2019.09.18-0",
      "freeform-tags": {},
      "id": "ocid1.image.oc1.eu-frankfurt-1.aaaaaaaayvqumqej62xz6rm7q4o2jdpjgvbn3yxa6zzybmmqop2ueksachzq",
      "launch-mode": "NATIVE",
      "launch-options": {
        "boot-volume-type": "PARAVIRTUALIZED",
        "firmware": "UEFI_64",
        "is-consistent-volume-naming-enabled": true,
        "is-pv-encryption-in-transit-enabled": true,
        "network-type": "PARAVIRTUALIZED",
        "remote-data-volume-type": "PARAVIRTUALIZED"
      },
      "lifecycle-state": "AVAILABLE",
      "operating-system": "Canonical Ubuntu",
      "operating-system-version": "18.04",
      "size-in-mbs": 47694,
      "time-created": "2019-09-23T18:37:11.566000+00:00"
    },
    {
      "agent-features": null,
      "base-image-id": null,
      "compartment-id": null,
      "create-image-allowed": true,
      "defined-tags": {},
      "display-name": "Canonical-Ubuntu-18.04-2019.08.14-0",
      "freeform-tags": {},
      "id": "ocid1.image.oc1.eu-frankfurt-1.aaaaaaaa2c2cncycdx7h6vvnmcwkbvduxxbq3hog5vq3pt56wisfzvo5v4fq",
      "launch-mode": "NATIVE",
      "launch-options": {
        "boot-volume-type": "PARAVIRTUALIZED",
        "firmware": "UEFI_64",
        "is-consistent-volume-naming-enabled": true,
        "is-pv-encryption-in-transit-enabled": true,
        "network-type": "PARAVIRTUALIZED",
        "remote-data-volume-type": "PARAVIRTUALIZED"
      },
      "lifecycle-state": "AVAILABLE",
      "operating-system": "Canonical Ubuntu",
      "operating-system-version": "18.04",
      "size-in-mbs": 47694,
      "time-created": "2019-08-15T12:52:41.439000+00:00"
    },
    {
      "agent-features": null,
      "base-image-id": null,
      "compartment-id": null,
      "create-image-allowed": true,
      "defined-tags": {},
      "display-name": "Canonical-Ubuntu-16.04-Minimal-2019.10.08-0",
      "freeform-tags": {},
      "id": "ocid1.image.oc1.eu-frankfurt-1.aaaaaaaa62jg6btz55to27cwodftpuv4vztkoo5d4gf5gjpzm7uuvveeehla",
      "launch-mode": "NATIVE",
      "launch-options": {
        "boot-volume-type": "PARAVIRTUALIZED",
        "firmware": "UEFI_64",
        "is-consistent-volume-naming-enabled": true,
        "is-pv-encryption-in-transit-enabled": true,
        "network-type": "PARAVIRTUALIZED",
        "remote-data-volume-type": "PARAVIRTUALIZED"
      },
      "lifecycle-state": "AVAILABLE",
      "operating-system": "Canonical Ubuntu",
      "operating-system-version": "16.04 Minimal",
      "size-in-mbs": 47694,
      "time-created": "2019-10-11T20:19:41.973000+00:00"
    },
    {
      "agent-features": null,
      "base-image-id": null,
      "compartment-id": null,
      "create-image-allowed": true,
      "defined-tags": {},
      "display-name": "Canonical-Ubuntu-16.04-Minimal-2019.09.20-0",
      "freeform-tags": {},
      "id": "ocid1.image.oc1.eu-frankfurt-1.aaaaaaaa2gsmfyhjo3asldljzigke6tvrqkmsjwxzikz7zbogebstgwdmnna",
      "launch-mode": "NATIVE",
      "launch-options": {
        "boot-volume-type": "PARAVIRTUALIZED",
        "firmware": "UEFI_64",
        "is-consistent-volume-naming-enabled": true,
        "is-pv-encryption-in-transit-enabled": true,
        "network-type": "PARAVIRTUALIZED",
        "remote-data-volume-type": "PARAVIRTUALIZED"
      },
      "lifecycle-state": "AVAILABLE",
      "operating-system": "Canonical Ubuntu",
      "operating-system-version": "16.04 Minimal",
      "size-in-mbs": 47694,
      "time-created": "2019-09-23T18:39:29.613000+00:00"
    },
    {
      "agent-features": null,
      "base-image-id": null,
      "compartment-id": null,
      "create-image-allowed": true,
      "defined-tags": {},
      "display-name": "Canonical-Ubuntu-16.04-Minimal-2019.08.13-0",
      "freeform-tags": {},
      "id": "ocid1.image.oc1.eu-frankfurt-1.aaaaaaaawq7gbe2ddoon77l5vk4jrau4hqj542rbvamd7ad7rgf5rzplntlq",
      "launch-mode": "NATIVE",
      "launch-options": {
        "boot-volume-type": "PARAVIRTUALIZED",
        "firmware": "UEFI_64",
        "is-consistent-volume-naming-enabled": true,
        "is-pv-encryption-in-transit-enabled": true,
        "network-type": "PARAVIRTUALIZED",
        "remote-data-volume-type": "PARAVIRTUALIZED"
      },
      "lifecycle-state": "AVAILABLE",
      "operating-system": "Canonical Ubuntu",
      "operating-system-version": "16.04 Minimal",
      "size-in-mbs": 47694,
      "time-created": "2019-08-16T14:37:02.652000+00:00"
    },
    {
      "agent-features": null,
      "base-image-id": null,
      "compartment-id": null,
      "create-image-allowed": true,
      "defined-tags": {},
      "display-name": "Canonical-Ubuntu-16.04-Gen2-GPU-2019.10.11-0",
      "freeform-tags": {},
      "id": "ocid1.image.oc1.eu-frankfurt-1.aaaaaaaag4r73dfsqai35m34wat7fu2vjffwe3qrfve6xlxpiwgj3o62f6fq",
      "launch-mode": "NATIVE",
      "launch-options": {
        "boot-volume-type": "PARAVIRTUALIZED",
        "firmware": "UEFI_64",
        "is-consistent-volume-naming-enabled": true,
        "is-pv-encryption-in-transit-enabled": true,
        "network-type": "PARAVIRTUALIZED",
        "remote-data-volume-type": "PARAVIRTUALIZED"
      },
      "lifecycle-state": "AVAILABLE",
      "operating-system": "Canonical Ubuntu",
      "operating-system-version": "16.04",
      "size-in-mbs": 47694,
      "time-created": "2019-10-13T00:27:53.478000+00:00"
    },
    {
      "agent-features": null,
      "base-image-id": null,
      "compartment-id": null,
      "create-image-allowed": true,
      "defined-tags": {},
      "display-name": "Canonical-Ubuntu-16.04-Gen2-GPU-2019.09.23-0",
      "freeform-tags": {},
      "id": "ocid1.image.oc1.eu-frankfurt-1.aaaaaaaafeusgtl56dukad6azreujthumiuswrmd7uyhshex2qj34gzir4ma",
      "launch-mode": "NATIVE",
      "launch-options": {
        "boot-volume-type": "PARAVIRTUALIZED",
        "firmware": "UEFI_64",
        "is-consistent-volume-naming-enabled": true,
        "is-pv-encryption-in-transit-enabled": true,
        "network-type": "PARAVIRTUALIZED",
        "remote-data-volume-type": "PARAVIRTUALIZED"
      },
      "lifecycle-state": "AVAILABLE",
      "operating-system": "Canonical Ubuntu",
      "operating-system-version": "16.04",
      "size-in-mbs": 47694,
      "time-created": "2019-09-23T18:42:58.888000+00:00"
    },
    {
      "agent-features": null,
      "base-image-id": null,
      "compartment-id": null,
      "create-image-allowed": true,
      "defined-tags": {},
      "display-name": "Canonical-Ubuntu-16.04-Gen2-GPU-2019.08.16-0",
      "freeform-tags": {},
      "id": "ocid1.image.oc1.eu-frankfurt-1.aaaaaaaaedcibg3rfb5abd6hjd7pmh3yb5d6xy4io73x7locjhaf4rfi7lfq",
      "launch-mode": "NATIVE",
      "launch-options": {
        "boot-volume-type": "PARAVIRTUALIZED",
        "firmware": "UEFI_64",
        "is-consistent-volume-naming-enabled": true,
        "is-pv-encryption-in-transit-enabled": true,
        "network-type": "PARAVIRTUALIZED",
        "remote-data-volume-type": "PARAVIRTUALIZED"
      },
      "lifecycle-state": "AVAILABLE",
      "operating-system": "Canonical Ubuntu",
      "operating-system-version": "16.04",
      "size-in-mbs": 47694,
      "time-created": "2019-08-16T18:42:45.861000+00:00"
    },
    {
      "agent-features": null,
      "base-image-id": null,
      "compartment-id": null,
      "create-image-allowed": true,
      "defined-tags": {},
      "display-name": "Canonical-Ubuntu-16.04-2019.10.10-0",
      "freeform-tags": {},
      "id": "ocid1.image.oc1.eu-frankfurt-1.aaaaaaaaotyxpitkydu5gc2o2youk4q2hvjtpmsh2g3jrlvfbp7advxzgexq",
      "launch-mode": "NATIVE",
      "launch-options": {
        "boot-volume-type": "PARAVIRTUALIZED",
        "firmware": "UEFI_64",
        "is-consistent-volume-naming-enabled": true,
        "is-pv-encryption-in-transit-enabled": true,
        "network-type": "PARAVIRTUALIZED",
        "remote-data-volume-type": "PARAVIRTUALIZED"
      },
      "lifecycle-state": "AVAILABLE",
      "operating-system": "Canonical Ubuntu",
      "operating-system-version": "16.04",
      "size-in-mbs": 47694,
      "time-created": "2019-10-11T20:15:16.854000+00:00"
    },
    {
      "agent-features": null,
      "base-image-id": null,
      "compartment-id": null,
      "create-image-allowed": true,
      "defined-tags": {},
      "display-name": "Canonical-Ubuntu-16.04-2019.09.18-0",
      "freeform-tags": {},
      "id": "ocid1.image.oc1.eu-frankfurt-1.aaaaaaaa4rm3qqlkjyb3u7t64677i57ietthiqsvc2h34autj57i66rbzuna",
      "launch-mode": "NATIVE",
      "launch-options": {
        "boot-volume-type": "PARAVIRTUALIZED",
        "firmware": "UEFI_64",
        "is-consistent-volume-naming-enabled": true,
        "is-pv-encryption-in-transit-enabled": true,
        "network-type": "PARAVIRTUALIZED",
        "remote-data-volume-type": "PARAVIRTUALIZED"
      },
      "lifecycle-state": "AVAILABLE",
      "operating-system": "Canonical Ubuntu",
      "operating-system-version": "16.04",
      "size-in-mbs": 47694,
      "time-created": "2019-09-23T18:43:21.108000+00:00"
    },
    {
      "agent-features": null,
      "base-image-id": null,
      "compartment-id": null,
      "create-image-allowed": true,
      "defined-tags": {},
      "display-name": "Canonical-Ubuntu-16.04-2019.08.14-0",
      "freeform-tags": {},
      "id": "ocid1.image.oc1.eu-frankfurt-1.aaaaaaaaguuudmn7kx7wcy3knxqe663bpbz6rhc42zxqt6wdqvght6az3tpq",
      "launch-mode": "NATIVE",
      "launch-options": {
        "boot-volume-type": "PARAVIRTUALIZED",
        "firmware": "UEFI_64",
        "is-consistent-volume-naming-enabled": true,
        "is-pv-encryption-in-transit-enabled": true,
        "network-type": "PARAVIRTUALIZED",
        "remote-data-volume-type": "PARAVIRTUALIZED"
      },
      "lifecycle-state": "AVAILABLE",
      "operating-system": "Canonical Ubuntu",
      "operating-system-version": "16.04",
      "size-in-mbs": 47694,
      "time-created": "2019-08-16T16:33:19.063000+00:00"
    }
  ]
}
